CHANGES.txt
LICENSE.txt
MANIFEST.in
README.txt
setup.py
js/__init__.py
js.mocha.egg-info/PKG-INFO
js.mocha.egg-info/SOURCES.txt
js.mocha.egg-info/dependency_links.txt
js.mocha.egg-info/entry_points.txt
js.mocha.egg-info/namespace_packages.txt
js.mocha.egg-info/not-zip-safe
js.mocha.egg-info/requires.txt
js.mocha.egg-info/top_level.txt
js/mocha/__init__.py
js/mocha/test_mocha.txt
js/mocha/resources/mocha.css
js/mocha/resources/mocha.js