Metadata-Version: 1.0
Name: js.mocha
Version: 2.2.5
Summary: Fanstatic packaging of Mocha
Home-page: UNKNOWN
Author: Fanstatic Developers
Author-email: fanstatic@googlegroups.com
License: BSD
Platform: UNKNOWN
